.travis.yml
licence
pyproject.toml
readme.md
requirements-dev.txt
requirements.txt
setup.cfg
setup.py
tox.ini
mail_serv.egg-info/PKG-INFO
mail_serv.egg-info/SOURCES.txt
mail_serv.egg-info/dependency_links.txt
mail_serv.egg-info/entry_points.txt
mail_serv.egg-info/not-zip-safe
mail_serv.egg-info/pbr.json
mail_serv.egg-info/requires.txt
mail_serv.egg-info/top_level.txt
src/readme.md
src/main/readme.md
src/main/mail_serv/__init__.py
src/main/mail_serv/arkon.py
src/main/mail_serv/command.py
src/main/mail_serv/config.py
src/main/mail_serv/filer.py
src/main/mail_serv/keeper.py
src/main/mail_serv/logging.py
src/main/mail_serv/maintain.py
src/main/mail_serv/process.py
src/main/mail_serv/procname.py
src/main/mail_serv/profiler.py
src/main/mail_serv/remote.py
src/main/mail_serv/replicate.py
src/main/mail_serv/sieve.py
src/main/mail_serv/subscribe.py
src/main/mail_serv/support.py
src/main/mail_serv/syncer.py
src/main/mail_serv/tinker.py
src/main/mail_serv/user.py
src/main/mail_serv/etc/readme.md
src/main/mail_serv/etc/systemd/system/arkon.service
src/main/mail_serv/etc/systemd/system/mail-keeper.service
src/main/mail_serv/etc/systemd/system/mail-keeper.timer
src/main/mail_serv/etc/systemd/system/mail-syncer.service
src/main/mail_serv/etc/systemd/system/opendkim.service
src/main/mail_serv/etc/systemd/system/postfix.service
src/main/mail_serv/etc/systemd/system/tinc.service
src/main/mail_serv/etc/systemd/system/tinc@.service
src/main/mail_serv/etc/sysusers.d/01-work.conf
src/main/mail_serv/etc/sysusers.d/02-service.conf
src/main/mail_serv/etc/tinc/readme.md
src/main/mail_serv/etc/tinc/mail/subnet-down
src/main/mail_serv/etc/tinc/mail/subnet-up
src/main/mail_serv/etc/tinc/mail/tinc-down
src/main/mail_serv/etc/tinc/mail/tinc-up
src/main/mail_serv/etc/tinc/mail/conf.d/readme.md
src/main/mail_serv/etc/tinc/mail/hosts/readme.md
src/main/mail_serv/etc/tinc/mail/nodes/readme.md
src/test/readme.md
src/test/mail_serv_test/.gitignore
src/test/mail_serv_test/__init__.py
src/test/mail_serv_test/arkon_test.py
src/test/mail_serv_test/command_test.py
src/test/mail_serv_test/config_test.py
src/test/mail_serv_test/filer_test.py
src/test/mail_serv_test/keeper_test.py
src/test/mail_serv_test/logging_test.py
src/test/mail_serv_test/mailbox_test.py
