Metadata-Version: 2.1
Name: mail-serv
Version: 0.7.1.dev1
Summary: Mail Service
Home-page: https://github.com/random-python/mail_serv
Author: Andrei Pozolotin
Author-email: andrei.pozolotin@gmail.com
License: Apache-2
Keywords: systemd,dovecot,postfix,getmail,tinc
Platform: UNKNOWN
Classifier: Development Status :: 4 - Beta
Classifier: Environment :: Console
Classifier: Intended Audience :: Developers
Classifier: Intended Audience :: Information Technology
Classifier: Intended Audience :: System Administrators
Classifier: License :: OSI Approved :: Apache Software License
Classifier: Operating System :: POSIX :: Linux
Classifier: Programming Language :: Python
Classifier: Programming Language :: Python :: 3.8
Classifier: Programming Language :: Python :: 3.9
Classifier: Programming Language :: Python :: 3.10
Classifier: Topic :: System :: Systems Administration
Classifier: Topic :: Terminals
Classifier: Topic :: Utilities
Requires-Python: >=3.8
